source_slack/__init__.py
source_slack/components/__init__.py
source_slack/components/channel_members_extractor.py
source_slack/components/join_channels.py
source_slack/components/slack_api_budget.py
source_slack/components/threads_partition_router.py
source_slack/config_migrations.py
source_slack/manifest.yaml
source_slack/run.py
source_slack/schemas/channel_members.json
source_slack/schemas/channel_messages.json
source_slack/schemas/channels.json
source_slack/schemas/threads.json
source_slack/schemas/users.json
source_slack/source.py
source_slack/spec.json
source_slack/utils.py
airbyte_source_slack-3.0.0.dist-info/METADATA
airbyte_source_slack-3.0.0.dist-info/WHEEL
airbyte_source_slack-3.0.0.dist-info/entry_points.txt
airbyte_source_slack-3.0.0.dist-info/RECORD
