Metadata-Version: 2.1
Name: airbyte-source-slack
Version: 3.0.0
Summary: Source implementation for Slack.
Home-page: https://airbyte.com
License: ELv2
Author: Airbyte
Author-email: contact@airbyte.io
Requires-Python: >=3.10,<3.12
Classifier: License :: Other/Proprietary License
Classifier: Programming Language :: Python :: 3
Classifier: Programming Language :: Python :: 3.10
Classifier: Programming Language :: Python :: 3.11
Requires-Dist: airbyte-cdk (>=6,<7)
Requires-Dist: freezegun (>=1.4.0,<2.0.0)
Requires-Dist: pendulum (==2.1.2)
Project-URL: Documentation, https://docs.airbyte.com/integrations/sources/slack
Project-URL: Repository, https://github.com/airbytehq/airbyte
